acte-0.0.15.dist-info/METADATA
acte-0.0.15.dist-info/WHEEL
acte-0.0.15.dist-info/entry_points.txt
acte-0.0.15.dist-info/licenses/LICENSE
acte/__init__.py
acte/build/__init__.py
acte/build/builder.py
acte/build/component.py
acte/build/type.py
acte/build/viewer/__init__.py
acte/build/viewer/button_viewer.py
acte/build/viewer/cache_viewer.py
acte/build/viewer/common/__init__.py
acte/build/viewer/common/base.py
acte/build/viewer/common/exception.py
acte/build/viewer/component_viewer.py
acte/build/viewer/div_viewer.py
acte/build/viewer/dyna_viewer.py
acte/build/viewer/input_viewer.py
acte/build/viewer/text_viewer.py
acte/build/viewer/viewer.py
acte/chatbot/__init__.py
acte/chatbot/chatbot.py
acte/chatbot/openai_chatbot.py
acte/chatbot/tools.py
acte/common/__init__.py
acte/common/util.py
acte/context/__init__.py
acte/context/context.py
acte/context/context_obj.py
acte/executor/__init__.py
acte/executor/action_type.py
acte/executor/executor.py
acte/node/__init__.py
acte/node/element/__init__.py
acte/node/element/block/__init__.py
acte/node/element/block/block.py
acte/node/element/block/div.py
acte/node/element/block/root.py
acte/node/element/element.py
acte/node/element/inline/__init__.py
acte/node/element/inline/button.py
acte/node/element/inline/inline.py
acte/node/element/inline/input.py
acte/node/element/inline/text.py
acte/node/implement/__init__.py
acte/node/implement/container.py
acte/node/implement/interactive.py
acte/node/node.py
acte/node/virtual/__init__.py
acte/node/virtual/cache.py
acte/node/virtual/component_node.py
acte/node/virtual/dyna.py
acte/node/virtual/virtual.py
acte/render/__init__.py
acte/render/html_renderer.py
acte/render/renderer.py
acte/schema/__init__.py
acte/schema/arr_schema.py
acte/schema/bool_schema.py
acte/schema/int_schema.py
acte/schema/null_schema.py
acte/schema/num_schema.py
acte/schema/obj_schema.py
acte/schema/schema.py
acte/schema/str_schema.py
acte/server/__init__.py
acte/server/chatbot_bp.py
acte/server/server.py
acte/server/static/assets/index-AyquRAp_.css
acte/server/static/assets/index-DeGh3O0O.js
acte/server/static/assets/logo-DwUUYqt5.svg
acte-0.0.15.dist-info/RECORD
