Metadata-Version: 2.1
Name: acte
Version: 0.0.15
Summary: A framework to build Tools for AI Agents, a GUI-like solution to enhance Function Calling.
Keywords: ai,agent,tool,framework,llm,function calling
Author-Email: j66n <jonathan.nuance@gmail.com>
License: MIT
Classifier: Programming Language :: Python :: 3
Classifier: Programming Language :: Python :: 3.10
Classifier: Programming Language :: Python :: 3.11
Classifier: Programming Language :: Python :: 3.12
Classifier: Programming Language :: Python :: 3 :: Only
Classifier: License :: OSI Approved :: MIT License
Classifier: Operating System :: OS Independent
Classifier: Development Status :: 3 - Alpha
Project-URL: Homepage, https://github.com/acte-all/acte
Requires-Python: >=3.10
Requires-Dist: aiohttp==3.10.5
Requires-Dist: starlette==0.38.2
Requires-Dist: uvicorn==0.30.6
Requires-Dist: jsonschema==4.23.0
